Workbook

Sheet Start Here
A1: Tampa Vendor Bench
A2: A one-workbook system for keeping reliable, fairly priced trades on call for Tampa rentals.
A4: How to use it
A5: 1. Properties tab: list each rental once. The Job Log dropdown reads from it.
A6: 2. Vendor Bench tab: add every person you have vetted. Yellow cells are yours to fill. Jobs, spend and last-used update themselves from the Job Log.
A7: 3. Job Log tab: one row per job. Pick the property and vendor from the dropdowns, enter quote and paid, rate the job 1 to 5.
A8: 4. Triage Guide tab: before you call anyone, find the issue here. It tells you which trade, whether a license is legally required, how urgent it is, and a typical Tampa price so you know when a quote is high.
A9: 5. Tampa Sourcing tab: where to find new people when a bench slot is empty. Ranked by how well they filter for quality.
A10: 6. Vetting Checklist tab: the six checks to run before anyone gets a key. Every check is a free online lookup.
A12: Bench rules that keep prices low
A13: Keep 2 to 3 people per trade. One primary, one backup. A vendor who knows he is your default gets all the small jobs and prices them lower.
A14: Route every small job through the handyman first. Only escalate to a licensed plumber or electrician when the Triage Guide says the law requires it.
... A23: Built 2026-09-08.

Sheet Properties
A1: Property nickname | B1: Street address | C1: City / ZIP | D1: Type | E1: Tenant name | F1: Tenant phone | G1: Lockbox / access note | H1: Water heater / AC age | I1: Notes
A2: Example: Seminole Hts | B2: 123 N Example St | C2: Tampa 33603 | D2: SFH 3/2 | E2: Jane Tenant | F2: 813-555-0100 | G2: Lockbox 4821 on side gate | H2: AC 2019, WH 2016 | I2: Older cast-iron drain lines

Sheet Vendor Bench
A1: Vendor name | B1: Company | C1: Trade | D1: Phone | E1: Email / text | F1: Role | G1: Status | H1: FL license # | I1: License type | J1: License verified (date) | K1: GL insurance expiry | L1: Days to expiry | M1: Workers comp (Y / Exempt / None) | N1: Rate | O1: Trip / min charge | P1: Response time | Q1: Found via | R1: Jobs done | S1: Total paid | T1: Avg rating | U1: Last used | V1: Notes
A2: Example: Mike R. | B2: Mike's Home Repair LLC | C2: Handyman | D2: 813-555-0101 | E2: mike@example.com | F2: Primary | G2: Active | H2: n/a (under $1k jobs) | I2: None (handyman) | J2: 2026-09-01 | K2: 46461 | L2: =IF(K2="","",K2-TODAY()) -> 187 | M2: Exempt | N2: $65/hr | O2: $85 first hour | P2: Same day | Q2: Tampa REIA | R2: =IF(A2="","",COUNTIF('Job Log'!$E:$E,A2)) -> 1 | S2: =IF(A2="","",SUMIFS('Job Log'!$H:$H,'Job Log'!$E:$E,A2)) -> 110 | T2: =IF(OR(A2="",COUNTIFS('Job Log'!$E:$E,A2,'Job Log'!$I:$I,">0")=0),"",AVERAGEIFS('Job Log'!$I:$I,'Job Log'!$E:$E,A2,'Job Log'!$I:$I,">0")) -> 5 | U2: =IF(OR(A2="",COUNTIF('Job Log'!$E:$E,A2)=0),"",SUMPRODUCT(MAX(('Job Log'!$E$2:$E$500=A2)*'Job Log'!$A$2:$A$500))) -> 46266 | V2: Does drywall, paint, fixtures, fences. Will not touch panel or pipe cuts.
A3: Emmanuel Fenelon | B3: Fenelon Handyman Services LLC | C3: Handyman | D3: (786) 509-5555 | E3: https://fenelonhandymanservices.com/ | F3: Primary | G3: Active | H3: n/a (handyman, under $1k jobs) | I3: None (handyman exemption) | J3: n/a, handyman exemption (jobs under $1,000, no plumbing/electrical) | L3: =IF(K3="","",K3-TODAY()) | M3: No policy or exemption on file (FL DWC, 9/8/2026). Ask for proof before first job. | N3: Flat-rate per job, 2-hr minimum | P3: Prompt scheduling per reviews | Q3: Thumbtack + Google | R3: =IF(A3="","",COUNTIF('Job Log'!$E:$E,A3)) -> 0 | S3: =IF(A3="","",SUMIFS('Job Log'!$H:$H,'Job Log'!$E:$E,A3)) -> 0 | T3: =IF(OR(A3="",COUNTIFS('Job Log'!$E:$E,A3,'Job Log'!$I:$I,">0")=0),"",AVERAGEIFS('Job Log'!$I:$I,'Job Log'!$E:$E,A3,'Job Log'!$I:$I,">0")) | U3: =IF(OR(A3="",COUNTIF('Job Log'!$E:$E,A3)=0),"",SUMPRODUCT(MAX(('Job Log'!$E$2:$E$500=A3)*'Job Log'!$A$2:$A$500))) | V3: 8-person crew, all of Hillsborough + Pinellas/Pasco. Fully insured, COI on request. Routes plumbing/electrical to licensed partners. Serves landlords and PM jobs. Bilingual.
A4: Wilfredo Lopez | B4: WL Handyman Service LLC | C4: Handyman | D4: (813) 330-0356 | E4: https://wlhandymanservice.com/ | F4: Backup | G4: Active | H4: n/a (handyman, under $1k jobs) | I4: None (handyman exemption) | J4: n/a, handyman exemption (jobs under $1,000, no plumbing/electrical) | L4: =IF(K4="","",K4-TODAY()) | M4: No policy or exemption on file (FL DWC, 9/8/2026). Ask for proof before first job. | N4: Call for quote, free estimate | P4: Same or next day advertised | Q4: Yelp + Google | R4: =IF(A4="","",COUNTIF('Job Log'!$E:$E,A4)) -> 0 | S4: =IF(A4="","",SUMIFS('Job Log'!$H:$H,'Job Log'!$E:$E,A4)) -> 0 | T4: =IF(OR(A4="",COUNTIFS('Job Log'!$E:$E,A4,'Job Log'!$I:$I,">0")=0),"",AVERAGEIFS('Job Log'!$I:$I,'Job Log'!$E:$E,A4,'Job Log'!$I:$I,">0")) | U4: =IF(OR(A4="",COUNTIF('Job Log'!$E:$E,A4)=0),"",SUMPRODUCT(MAX(('Job Log'!$E$2:$E$500=A4)*'Job Log'!$A$2:$A$500))) | V4: South Tampa owner-operator since 2019, covers Tampa to Brandon/Riverview and Pinellas. Registered and insured. Explicit landlord turnover service, rent-ready in 3-5 days. Ask for COI.
A5: Martin (owner) | B5: Tampa Sarasota Handyman, LLC | C5: Handyman | D5: (813) 733-0052 | E5: https://tampasarasotahandyman.com/ | F5: Backup (South Shore) | G5: Active | H5: n/a (handyman, under $1k jobs) | I5: None (handyman exemption) | J5: n/a, handyman exemption (jobs under $1,000, no plumbing/electrical) | L5: =IF(K5="","",K5-TODAY()) | M5: No policy or exemption on file (FL DWC, 9/8/2026). Ask for proof before first job. | N5: Call for quote, no-surprise written quotes | Q5: Google + Angi | R5: =IF(A5="","",COUNTIF('Job Log'!$E:$E,A5)) -> 0 | S5: =IF(A5="","",SUMIFS('Job Log'!$H:$H,'Job Log'!$E:$E,A5)) -> 0 | T5: =IF(OR(A5="",COUNTIFS('Job Log'!$E:$E,A5,'Job Log'!$I:$I,">0")=0),"",AVERAGEIFS('Job Log'!$I:$I,'Job Log'!$E:$E,A5,'Job Log'!$I:$I,">0")) | U5: =IF(OR(A5="",COUNTIF('Job Log'!$E:$E,A5)=0),"",SUMPRODUCT(MAX(('Job Log'!$E$2:$E$500=A5)*'Job Log'!$A$2:$A$500))) | V5: Riverview-based, best for South Shore: Riverview, Brandon, Apollo Beach, Ruskin, Sun City Center. $1M liability stated. Rental turnover and make-ready service.
A6: George Barnes | B6: George Barnes Handyman Services LLC | C6: Handyman | D6: (813) 390-3410 | E6: https://www.handymangeorgebarnes.com/ | F6: Candidate | G6: Active | H6: n/a (states not a licensed contractor) | I6: None (handyman exemption) | J6: n/a, handyman exemption (jobs under $1,000, no plumbing/electrical) | L6: =IF(K6="","",K6-TODAY()) | M6: No policy or exemption on file (FL DWC, 9/8/2026). Ask for proof before first job. | N6: Free in-home estimate; beats or matches written estimates | Q6: BBB + Yelp | R6: =IF(A6="","",COUNTIF('Job Log'!$E:$E,A6)) -> 0 | S6: =IF(A6="","",SUMIFS('Job Log'!$H:$H,'Job Log'!$E:$E,A6)) -> 0 | T6: =IF(OR(A6="",COUNTIFS('Job Log'!$E:$E,A6,'Job Log'!$I:$I,">0")=0),"",AVERAGEIFS('Job Log'!$I:$I,'Job Log'!$E:$E,A6,'Job Log'!$I:$I,">0")) | U6: =IF(OR(A6="",COUNTIF('Job Log'!$E:$E,A6)=0),"",SUMPRODUCT(MAX(('Job Log'!$E$2:$E$500=A6)*'Job Log'!$A$2:$A$500))) | V6: New Tampa / Wesley Chapel / Lutz corridor, in business since 1980. One-year labor guarantee. Insurance NOT stated on site, get a COI before first job. Works with property managers.
A7: Robert Coughlin | B7: Mr. Handyman (Citrus Park / Keystone) - franchise price reference | C7: Handyman | D7: (813) 694-1210 | E7: https://www.mrhandyman.com/citrus-park-keystone/ | F7: Reference (franchise/large shop) | G7: Active | H7: CGC1513681 | I7: Cert General Contractor | J7: 2026-09-09, Current/Active, exp 08/31/2028 | L7: =IF(K7="","",K7-TODAY()) | M7: Not checked (reference row) | N7: ~$158 first hour, then ~$108/hr | O7: $50 service fee included in first hour | Q7: BBB + HomeAdvisor | R7: =IF(A7="","",COUNTIF('Job Log'!$E:$E,A7)) -> 0 | S7: =IF(A7="","",SUMIFS('Job Log'!$H:$H,'Job Log'!$E:$E,A7)) -> 0 | T7: =IF(OR(A7="",COUNTIFS('Job Log'!$E:$E,A7,'Job Log'!$I:$I,">0")=0),"",AVERAGEIFS('Job Log'!$I:$I,'Job Log'!$E:$E,A7,'Job Log'!$I:$I,">0")) | U7: =IF(OR(A7="",COUNTIF('Job Log'!$E:$E,A7)=0),"",SUMPRODUCT(MAX(('Job Log'!$E$2:$E$500=A7)*'Job Log'!$A$2:$A$500))) | V7: Reference row: what franchise pricing looks like. A good independent lands 30-50% under this on the same punch list. Sister franchises cover Brandon and Lutz.
B8: Experts Plumbing Services, LLC | C8: Plumber | D8: 813-363-9726 | E8: https://expertsplumbingservices.com/ | F8: Primary | G8: Active | H8: CFC1428527 | I8: Cert Plumbing | J8: 2026-09-09, Current/Active, exp 08/31/2028 | L8: =IF(K8="","",K8-TODAY()) | M8: Not checked yet; request COI | N8: $105 service fee, waived if work done; drain stoppage $250-350; electric water heater installed from $1,205 | O8: $105, waived with work | P8: Mon-Fri 7-5, no weekends | Q8: Google + BBB | R8: =IF(A8="","",COUNTIF('Job Log'!$E:$E,A8)) | S8: =IF(A8="","",SUMIFS('Job Log'!$H:$H,'Job Log'!$E:$E,A8)) | T8: =IF(OR(A8="",COUNTIFS('Job Log'!$E:$E,A8,'Job Log'!$I:$I,">0")=0),"",AVERAGEIFS('Job Log'!$I:$I,'Job Log'!$E:$E,A8,'Job Log'!$I:$I,">0")) | U8: =IF(OR(A8="",COUNTIF('Job Log'!$E:$E,A8)=0),"",SUMPRODUCT(MAX(('Job Log'!$E$2:$E$500=A8)*'Job Log'!$A$2:$A$500))) | V8: North Tampa shop, all Hillsborough. Only indie with published flat rates. Property-management testimonial on site. No after-hours, pair with a 24/7 backup.
A9: Roger (owner) | B9: Llona Plumbing, Inc. | C9: Plumber | D9: 813-477-1870 | E9: https://llonaplumbing.com/ | F9: Backup (weekends) | G9: Active | H9: CFC1431902 | I9: Cert Plumbing | J9: 2026-09-09, Current/Active, exp 08/31/2028 | L9: =IF(K9="","",K9-TODAY()) | M9: Not checked yet; request COI | N9: $180/hr labor + $50 sewer machine; most stoppages under $250 | P9: 24 hrs Fri-Sun; Mon-Thu 8-5 | Q9: Google + BBB | R9: =IF(A9="","",COUNTIF('Job Log'!$E:$E,A9)) -> 0 | S9: =IF(A9="","",SUMIFS('Job Log'!$H:$H,'Job Log'!$E:$E,A9)) -> 0 | T9: =IF(OR(A9="",COUNTIFS('Job Log'!$E:$E,A9,'Job Log'!$I:$I,">0")=0),"",AVERAGEIFS('Job Log'!$I:$I,'Job Log'!$E:$E,A9,'Job Log'!$I:$I,">0")) | U9: =IF(OR(A9="",COUNTIF('Job Log'!$E:$E,A9)=0),"",SUMPRODUCT(MAX(('Job Log'!$E$2:$E$500=A9)*'Job Log'!$A$2:$A$500))) | V9: Family-owned since 2004, West Tampa shop, covers Hillsborough/Pinellas/Pasco/Manatee. Weekend 24-hr coverage makes this the emergency backup.
A10: Anthony Dang | B10: ALCA Plumbing Inc. | C10: Plumber | D10: 813-780-2222 | E10: https://www.alcaplumbinginc.com/ | F10: Backup (North) | G10: Active | H10: CFC1426773 | I10: Cert Plumbing | J10: 2026-09-09, Current/Active, exp 08/31/2028 | L10: =IF(K10="","",K10-TODAY()) | M10: Not checked yet; request COI | N10: Tub stoppage $280; main sewer line $320-350 | P10: 7 days, 7am-7pm | Q10: Google + BBB | R10: =IF(A10="","",COUNTIF('Job Log'!$E:$E,A10)) -> 0 | S10: =IF(A10="","",SUMIFS('Job Log'!$H:$H,'Job Log'!$E:$E,A10)) -> 0 | T10: =IF(OR(A10="",COUNTIFS('Job Log'!$E:$E,A10,'Job Log'!$I:$I,">0")=0),"",AVERAGEIFS('Job Log'!$I:$I,'Job Log'!$E:$E,A10,'Job Log'!$I:$I,">0")) | U10: =IF(OR(A10="",COUNTIF('Job Log'!$E:$E,A10)=0),"",SUMPRODUCT(MAX(('Job Log'!$E$2:$E$500=A10)*'Job Log'!$A$2:$A$500))) | V10: Owner-operated since 2005, Wesley Chapel base, best for North Tampa / New Tampa / Pasco-line houses. Owner answers the phone and supervises jobs.
A11: Jerry Calhoun | B11: Son of a Plumber Inc. | C11: Plumber | D11: 813-368-6028 (call or text) | E11: https://sonofaplumberinc.com/ | F11: Candidate | G11: Active | H11: CFC1430455 | I11: Cert Plumbing | J11: 2026-09-09, Current/Active, exp 08/31/2028 | L11: =IF(K11="","",K11-TODAY()) | M11: Not checked yet; request COI | N11: Call or text for quote; free second opinions | P11: Mon-Fri 8-5 | Q11: Yelp + Nextdoor | R11: =IF(A11="","",COUNTIF('Job Log'!$E:$E,A11)) -> 0 | S11: =IF(A11="","",SUMIFS('Job Log'!$H:$H,'Job Log'!$E:$E,A11)) -> 0 | T11: =IF(OR(A11="",COUNTIFS('Job Log'!$E:$E,A11,'Job Log'!$I:$I,">0")=0),"",AVERAGEIFS('Job Log'!$I:$I,'Job Log'!$E:$E,A11,'Job Log'!$I:$I,">0")) | U11: =IF(OR(A11="",COUNTIF('Job Log'!$E:$E,A11)=0),"",SUMPRODUCT(MAX(('Job Log'!$E$2:$E$500=A11)*'Job Log'!$A$2:$A$500))) | V11: One-man master plumber, Wesley Chapel / Temple Terrace / Land O Lakes. Cheapest structure (no dispatcher, no trucks to feed) but one person means no backup. Good water-heater swap reputation.
A12: Dave Cass | B12: Cass Plumbing, Inc. | C12: Plumber | D12: 813-265-9200 | E12: https://cassplumbingtampabay.com/ | F12: Candidate (volume) | G12: Active | H12: CFC057412 | I12: Cert Plumbing | J12: 2026-09-09, Current/Active, exp 08/31/2028 | L12: =IF(K12="","",K12-TODAY()) | M12: Not checked yet; request COI | N12: Call for quote; no trip fee; free estimates | O12: None advertised | P12: 24/7 | Q12: BBB + Google | R12: =IF(A12="","",COUNTIF('Job Log'!$E:$E,A12)) -> 0 | S12: =IF(A12="","",SUMIFS('Job Log'!$H:$H,'Job Log'!$E:$E,A12)) -> 0 | T12: =IF(OR(A12="",COUNTIFS('Job Log'!$E:$E,A12,'Job Log'!$I:$I,">0")=0),"",AVERAGEIFS('Job Log'!$I:$I,'Job Log'!$E:$E,A12,'Job Log'!$I:$I,">0")) | U12: =IF(OR(A12="",COUNTIF('Job Log'!$E:$E,A12)=0),"",SUMPRODUCT(MAX(('Job Log'!$E$2:$E$500=A12)*'Job Log'!$A$2:$A$500))) | V12: Bigger family shop since 2000, Tampa + Brandon offices, multiple trucks. Property managers in reviews cite fast tenant response and documentation. The volume-rate candidate for 60+ doors.
B13: Roto-Rooter Tampa - franchise price reference | C13: Plumber | D13: 813-980-6000 | E13: https://www.rotorooter.com/tampa/ | F13: Reference (franchise/large shop) | G13: Active | H13: CFC1429911 | I13: Cert Plumbing | J13: 2026-09-09, Current/Active, exp 08/31/2028 | L13: =IF(K13="","",K13-TODAY()) | M13: Not checked (reference row) | N13: Drain cleaning $225-600; after-hours +$100-200; reviews cite $560 holiday drain call | O13: None, baked into flat rate | P13: 24/7/365 | Q13: Google + BBB | R13: =IF(A13="","",COUNTIF('Job Log'!$E:$E,A13)) | S13: =IF(A13="","",SUMIFS('Job Log'!$H:$H,'Job Log'!$E:$E,A13)) | T13: =IF(OR(A13="",COUNTIFS('Job Log'!$E:$E,A13,'Job Log'!$I:$I,">0")=0),"",AVERAGEIFS('Job Log'!$I:$I,'Job Log'!$E:$E,A13,'Job Log'!$I:$I,">0")) | U13: =IF(OR(A13="",COUNTIF('Job Log'!$E:$E,A13)=0),"",SUMPRODUCT(MAX(('Job Log'!$E$2:$E$500=A13)*'Job Log'!$A$2:$A$500))) | V13: Reference row. Competent and fast, consistently 'pricey' in reviews, water-restoration upsell team follows the plumber. Member of Bay Area Apartment Association.
A14: Christopher Groves | B14: Groves Electric, Inc. | C14: Electrician | D14: 813-789-3400 | E14: https://www.groveselectricinc.com/ | F14: Primary | G14: Active | H14: EC13011132 | I14: Cert Electrical | J14: 2026-09-09, Current/Active, exp 08/31/2028 | L14: =IF(K14="","",K14-TODAY()) | M14: Not checked yet; request COI | N14: Free quotes, no trip charge | O14: None | P14: Owner on site within the hour per reviews | Q14: BBB + Yelp | R14: =IF(A14="","",COUNTIF('Job Log'!$E:$E,A14)) -> 0 | S14: =IF(A14="","",SUMIFS('Job Log'!$H:$H,'Job Log'!$E:$E,A14)) -> 0 | T14: =IF(OR(A14="",COUNTIFS('Job Log'!$E:$E,A14,'Job Log'!$I:$I,">0")=0),"",AVERAGEIFS('Job Log'!$I:$I,'Job Log'!$E:$E,A14,'Job Log'!$I:$I,">0")) | U14: =IF(OR(A14="",COUNTIF('Job Log'!$E:$E,A14)=0),"",SUMPRODUCT(MAX(('Job Log'!$E$2:$E$500=A14)*'Job Log'!$A$2:$A$500))) | V14: Family-run South Tampa shop since 1998. Best value signal of the group: no trip charge and reviews cite 'a lot done in one hour'. Tampa proper, not the far suburbs.
A15: Samuel Lemons | B15: Force Electric, Inc. | C15: Electrician | D15: 813-251-5559 | E15: https://www.forceelectricservice.com/ | F15: Backup | G15: Active | H15: EC0001712 | I15: Cert Electrical | J15: 2026-09-09, Current/Active, exp 08/31/2028 | L15: =IF(K15="","",K15-TODAY()) | M15: Not checked yet; request COI | N15: Flat rate per job, quoted before work; free estimates; plan members 15% off + no dispatch fee | O15: Dispatch fee for non-members, amount unpublished | Q15: Google + Yelp | R15: =IF(A15="","",COUNTIF('Job Log'!$E:$E,A15)) -> 0 | S15: =IF(A15="","",SUMIFS('Job Log'!$H:$H,'Job Log'!$E:$E,A15)) -> 0 | T15: =IF(OR(A15="",COUNTIFS('Job Log'!$E:$E,A15,'Job Log'!$I:$I,">0")=0),"",AVERAGEIFS('Job Log'!$I:$I,'Job Log'!$E:$E,A15,'Job Log'!$I:$I,">0")) | U15: =IF(OR(A15="",COUNTIF('Job Log'!$E:$E,A15)=0),"",SUMPRODUCT(MAX(('Job Log'!$E$2:$E$500=A15)*'Job Log'!$A$2:$A$500))) | V15: Since 1990, Carrollwood / Dale Mabry base, licensed Hillsborough + Pinellas + Pasco. Reviews say quotes come in under competitors. Background-checked techs.
A16: Brian Levinus | B16: Exodus Electric Corporation | C16: Electrician | D16: 813-444-4445 | E16: https://www.exoduselectric.com/ | F16: Backup (portfolio plan) | G16: Active | H16: EC13006236 | I16: Cert Electrical | J16: 2026-09-09, Current/Active, exp 08/31/2028 | L16: =IF(K16="","",K16-TODAY()) | M16: Not checked yet; request COI | N16: Diagnostic fee (unpublished), free estimates; after-hours rates apply | P16: After-hours + weekend emergency | Q16: BBB + Google | R16: =IF(A16="","",COUNTIF('Job Log'!$E:$E,A16)) -> 0 | S16: =IF(A16="","",SUMIFS('Job Log'!$H:$H,'Job Log'!$E:$E,A16)) -> 0 | T16: =IF(OR(A16="",COUNTIFS('Job Log'!$E:$E,A16,'Job Log'!$I:$I,">0")=0),"",AVERAGEIFS('Job Log'!$I:$I,'Job Log'!$E:$E,A16,'Job Log'!$I:$I,">0")) | U16: =IF(OR(A16="",COUNTIF('Job Log'!$E:$E,A16)=0),"",SUMPRODUCT(MAX(('Job Log'!$E$2:$E$500=A16)*'Job Log'!$A$2:$A$500))) | V16: The portfolio candidate: offers a written Property Management Maintenance Agreement (turnover, emergencies, annual inspections). Tampa + Brandon offices, 75-mile radius. Since 2007.
A17: Michael Tracy (owner); DBPR qualifier Robert Fistilla | B17: Lightning Bay Electric | C17: Electrician | D17: 813-897-2665 | E17: https://www.lightningbayelectric.com/ | F17: Candidate | G17: Active | H17: EC13013571 | I17: Cert Electrical | J17: 2026-09-09, Current/Active, exp 08/31/2028 | L17: =IF(K17="","",K17-TODAY()) | M17: Not checked yet; request COI | N17: Modest diagnostic fee applied to repair; firm price before work | P17: 24-hour emergency | Q17: Google + BBB | R17: =IF(A17="","",COUNTIF('Job Log'!$E:$E,A17)) -> 0 | S17: =IF(A17="","",SUMIFS('Job Log'!$H:$H,'Job Log'!$E:$E,A17)) -> 0 | T17: =IF(OR(A17="",COUNTIFS('Job Log'!$E:$E,A17,'Job Log'!$I:$I,">0")=0),"",AVERAGEIFS('Job Log'!$I:$I,'Job Log'!$E:$E,A17,'Job Log'!$I:$I,">0")) | U17: =IF(OR(A17="",COUNTIF('Job Log'!$E:$E,A17)=0),"",SUMPRODUCT(MAX(('Job Log'!$E$2:$E$500=A17)*'Job Log'!$A$2:$A$500))) | V17: New company (2024) but courts landlords directly: reviews from a PM running 42 properties. Riverview / East Hillsborough. Ask who the license qualifier is, the DBPR name differs from the owner on the site.
A18: Houle family | B18: Small Jobs Electric, Inc. | C18: Electrician | D18: 813-968-5856 | E18: https://www.smalljobselectric.com/ | F18: Candidate (after-hours) | G18: Active | H18: EC0003040 | I18: Cert Electrical | J18: 2026-09-09, Current/Active, exp 08/31/2028 | L18: =IF(K18="","",K18-TODAY()) | M18: Not checked yet; request COI | N18: Flat rate; $49 service fee applied to work | O18: $49 + $29 dispatch (waived for new customers) | P18: 24/7 | Q18: BBB + Angi | R18: =IF(A18="","",COUNTIF('Job Log'!$E:$E,A18)) -> 0 | S18: =IF(A18="","",SUMIFS('Job Log'!$H:$H,'Job Log'!$E:$E,A18)) -> 0 | T18: =IF(OR(A18="",COUNTIFS('Job Log'!$E:$E,A18,'Job Log'!$I:$I,">0")=0),"",AVERAGEIFS('Job Log'!$I:$I,'Job Log'!$E:$E,A18,'Job Log'!$I:$I,">0")) | U18: =IF(OR(A18="",COUNTIF('Job Log'!$E:$E,A18)=0),"",SUMPRODUCT(MAX(('Job Log'!$E$2:$E$500=A18)*'Job Log'!$A$2:$A$500))) | V18: 40-year residential shop, very high volume, 24/7. Reliable backup, but repeat reviews say flat-rate quotes run high. Use for after-hours, not for the everyday call.
B19: Mister Sparky of Tampa - franchise price reference | C19: Electrician | D19: 813-328-7210 | E19: https://www.mistersparky.com/tampa/ | F19: Reference (franchise/large shop) | G19: Active | H19: EC13008384 | I19: Cert Electrical | J19: 2026-09-09, Current/Active, exp 08/31/2028 | L19: =IF(K19="","",K19-TODAY()) | M19: Not checked (reference row) | N19: Flat rate; trip charge waived for club members; older complaint cites $59 service fee | P19: 24/7 | Q19: Google | R19: =IF(A19="","",COUNTIF('Job Log'!$E:$E,A19)) | S19: =IF(A19="","",SUMIFS('Job Log'!$H:$H,'Job Log'!$E:$E,A19)) | T19: =IF(OR(A19="",COUNTIFS('Job Log'!$E:$E,A19,'Job Log'!$I:$I,">0")=0),"",AVERAGEIFS('Job Log'!$I:$I,'Job Log'!$E:$E,A19,'Job Log'!$I:$I,">0")) | U19: =IF(OR(A19="",COUNTIF('Job Log'!$E:$E,A19)=0),"",SUMPRODUCT(MAX(('Job Log'!$E$2:$E$500=A19)*'Job Log'!$A$2:$A$500))) | V19: Reference row. Fast and professional; franchise-wide complaints center on high flat rates and panel/surge upsells.
A20: Hebert family | B20: 3H AC of Tampa | C20: HVAC | D20: (813) 979-4208 (call or text) | E20: https://3hac.com/ | F20: Backup (maintenance plan) | G20: Active | H20: CMC1249567 | I20: Cert Mechanical | J20: 2026-09-09, Current/Active, exp 08/31/2028 | L20: =IF(K20="","",K20-TODAY()) | M20: Not checked yet; request COI | N20: Maintenance plan $195/system/yr, 2 visits incl. coil clean, 10% off repairs, multi-system discounts; free phone troubleshooting | P20: Mon-Fri 7:30-7:30, weekends 8-6 | Q20: Google + BBB | R20: =IF(A20="","",COUNTIF('Job Log'!$E:$E,A20)) -> 0 | S20: =IF(A20="","",SUMIFS('Job Log'!$H:$H,'Job Log'!$E:$E,A20)) -> 0 | T20: =IF(OR(A20="",COUNTIFS('Job Log'!$E:$E,A20,'Job Log'!$I:$I,">0")=0),"",AVERAGEIFS('Job Log'!$I:$I,'Job Log'!$E:$E,A20,'Job Log'!$I:$I,">0")) | U20: =IF(OR(A20="",COUNTIF('Job Log'!$E:$E,A20)=0),"",SUMPRODUCT(MAX(('Job Log'!$E$2:$E$500=A20)*'Job Log'!$A$2:$A$500))) | V20: Family shop since 2002, North Tampa, Hillsborough/Pinellas/Pasco. Has a dedicated property-management HVAC page with per-system records. The portfolio maintenance-plan candidate.
A21: Rolando Mojarrieta | B21: Rolando's H.V.A.C., LLC | C21: HVAC | D21: (813) 373-6804 | E21: https://www.rolandoshvac.com/ | F21: Primary | G21: Active | H21: CAC1820272 | I21: Cert Air Conditioning | J21: 2026-09-09, Current/Active, exp 08/31/2028 | L21: =IF(K21="","",K21-TODAY()) | M21: Not checked yet; request COI | N21: $125 diagnostic, waived with repair; full system replacement $6,000-12,000 published | O21: $125, waived with repair | P21: Emergency repair advertised | Q21: Google + BBB | R21: =IF(A21="","",COUNTIF('Job Log'!$E:$E,A21)) -> 0 | S21: =IF(A21="","",SUMIFS('Job Log'!$H:$H,'Job Log'!$E:$E,A21)) -> 0 | T21: =IF(OR(A21="",COUNTIFS('Job Log'!$E:$E,A21,'Job Log'!$I:$I,">0")=0),"",AVERAGEIFS('Job Log'!$I:$I,'Job Log'!$E:$E,A21,'Job Log'!$I:$I,">0")) | U21: =IF(OR(A21="",COUNTIF('Job Log'!$E:$E,A21)=0),"",SUMPRODUCT(MAX(('Job Log'!$E$2:$E$500=A21)*'Job Log'!$A$2:$A$500))) | V21: Owner-operated since 2019, West Tampa, 5 counties. Huge review volume with a 'no upsell' theme. Publishes replacement price ranges, rare in this trade. Best everyday repair call.
A22: Patrick Fontana | B22: Fontana Brothers Heating & Air Conditioning, LLC | C22: HVAC | D22: (813) 252-1226 | E22: https://fontanabrothersair.com/ | F22: Backup | G22: Active | H22: CAC1817303 | I22: Cert Air Conditioning | J22: 2026-09-09, Current/Active, exp 08/31/2028 | L22: =IF(K22="","",K22-TODAY()) | M22: Not checked yet; request COI | N22: Call for quote; club plan 2 tune-ups/yr + 15% off parts and labor | Q22: BBB + Google | R22: =IF(A22="","",COUNTIF('Job Log'!$E:$E,A22)) -> 0 | S22: =IF(A22="","",SUMIFS('Job Log'!$H:$H,'Job Log'!$E:$E,A22)) -> 0 | T22: =IF(OR(A22="",COUNTIFS('Job Log'!$E:$E,A22,'Job Log'!$I:$I,">0")=0),"",AVERAGEIFS('Job Log'!$I:$I,'Job Log'!$E:$E,A22,'Job Log'!$I:$I,">0")) | U22: =IF(OR(A22="",COUNTIF('Job Log'!$E:$E,A22)=0),"",SUMPRODUCT(MAX(('Job Log'!$E$2:$E$500=A22)*'Job Log'!$A$2:$A$500))) | V22: Three brothers, West Tampa, since 2012, 5 counties. Reviews repeat 'honest' and 'reasonable rates'. No landlord program but a solid backup.
A23: Morales family | B23: Home Therapist Cooling, Heating, and Plumbing | C23: HVAC | D23: (813) 343-2212 | E23: https://callhometherapist.com/ | F23: Candidate | G23: Active | H23: CAC1819196 | I23: Cert Air Conditioning (also CFC1431159 plumbing) | J23: 2026-09-09, Current/Active, exp 08/31/2028 | L23: =IF(K23="","",K23-TODAY()) | M23: Not checked yet; request COI | N23: $89 tune-up promo; plans $120/$240/$480 per system/yr; $279 service-call minimum once repair approved, $120/hr after | O23: 'Free diagnosis' but $279 minimum applies when work is approved | P23: 24/7 dispatch, no after-hours surcharge advertised | Q23: Google + BBB | R23: =IF(A23="","",COUNTIF('Job Log'!$E:$E,A23)) -> 0 | S23: =IF(A23="","",SUMIFS('Job Log'!$H:$H,'Job Log'!$E:$E,A23)) -> 0 | T23: =IF(OR(A23="",COUNTIFS('Job Log'!$E:$E,A23,'Job Log'!$I:$I,">0")=0),"",AVERAGEIFS('Job Log'!$I:$I,'Job Log'!$E:$E,A23,'Job Log'!$I:$I,">0")) | U23: =IF(OR(A23="",COUNTIF('Job Log'!$E:$E,A23)=0),"",SUMPRODUCT(MAX(('Job Log'!$E$2:$E$500=A23)*'Job Log'!$A$2:$A$500))) | V23: North Tampa, since 2017, HVAC + plumbing under one roof. Explicit 'landlord and property manager' multi-property discount. Pricing pages contradict each other, pin the numbers down by phone before comparing.
A24: Jean Maalouf | B24: Tampa AC Services Inc | C24: HVAC | D24: (813) 993-4669 | E24: https://tampa-acservices.com/ | F24: Candidate | G24: Active | H24: CAC1822145 | I24: Cert Air Conditioning | J24: 2026-09-09, Current/Active, exp 08/31/2028 | L24: =IF(K24="","",K24-TODAY()) | M24: Not checked yet; request COI | N24: Maintenance plan $150/system/yr (1 visit), 10% off parts and labor, no overtime fees | P24: Open 24 hours | Q24: Google + BBB | R24: =IF(A24="","",COUNTIF('Job Log'!$E:$E,A24)) -> 0 | S24: =IF(A24="","",SUMIFS('Job Log'!$H:$H,'Job Log'!$E:$E,A24)) -> 0 | T24: =IF(OR(A24="",COUNTIFS('Job Log'!$E:$E,A24,'Job Log'!$I:$I,">0")=0),"",AVERAGEIFS('Job Log'!$I:$I,'Job Log'!$E:$E,A24,'Job Log'!$I:$I,">0")) | U24: =IF(OR(A24="",COUNTIF('Job Log'!$E:$E,A24)=0),"",SUMPRODUCT(MAX(('Job Log'!$E$2:$E$500=A24)*'Job Log'!$A$2:$A$500))) | V24: Youngest company here (2022), North Tampa. Lowest published plan price, thin third-party review depth. Trial-job candidate, not a primary.
B25: IERNA's Heating & Cooling - large-shop price reference | C25: HVAC | D25: (813) 578-7113 | E25: https://www.iernaair.com/ | F25: Reference (franchise/large shop) | G25: Active | H25: CAC1822278 | I25: Cert Air Conditioning | J25: 2026-09-09, Current/Active, exp 08/31/2028 | L25: =IF(K25="","",K25-TODAY()) | M25: Not checked (reference row) | N25: Diagnostic fee unpublished, waived with repair; reviews cite $89 and a $413 diagnostic complaint; membership 15% off | P25: 24-hour support | Q25: Google | R25: =IF(A25="","",COUNTIF('Job Log'!$E:$E,A25)) | S25: =IF(A25="","",SUMIFS('Job Log'!$H:$H,'Job Log'!$E:$E,A25)) | T25: =IF(OR(A25="",COUNTIFS('Job Log'!$E:$E,A25,'Job Log'!$I:$I,">0")=0),"",AVERAGEIFS('Job Log'!$I:$I,'Job Log'!$E:$E,A25,'Job Log'!$I:$I,">0")) | U25: =IF(OR(A25="",COUNTIF('Job Log'!$E:$E,A25)=0),"",SUMPRODUCT(MAX(('Job Log'!$E$2:$E$500=A25)*'Job Log'!$A$2:$A$500))) | V25: Reference row: 100 employees, 50 trucks, HVAC + plumbing + electrical. Responsive, but recurring complaints about surprise diagnostic charges and upsell pressure.
L26: =IF(K26="","",K26-TODAY()) | R26: =IF(A26="","",COUNTIF('Job Log'!$E:$E,A26)) | S26: =IF(A26="","",SUMIFS('Job Log'!$H:$H,'Job Log'!$E:$E,A26)) | T26: =IF(OR(A26="",COUNTIFS('Job Log'!$E:$E,A26,'Job Log'!$I:$I,">0")=0),"",AVERAGEIFS('Job Log'!$I:$I,'Job Log'!$E:$E,A26,'Job Log'!$I:$I,">0")) | U26: =IF(OR(A26="",COUNTIF('Job Log'!$E:$E,A26)=0),"",SUMPRODUCT(MAX(('Job Log'!$E$2:$E$500=A26)*'Job Log'!$A$2:$A$500)))
L27: =IF(K27="","",K27-TODAY()) | R27: =IF(A27="","",COUNTIF('Job Log'!$E:$E,A27)) | S27: =IF(A27="","",SUMIFS('Job Log'!$H:$H,'Job Log'!$E:$E,A27)) | T27: =IF(OR(A27="",COUNTIFS('Job Log'!$E:$E,A27,'Job Log'!$I:$I,">0")=0),"",AVERAGEIFS('Job Log'!$I:$I,'Job Log'!$E:$E,A27,'Job Log'!$I:$I,">0")) | U27: =IF(OR(A27="",COUNTIF('Job Log'!$E:$E,A27)=0),"",SUMPRODUCT(MAX(('Job Log'!$E$2:$E$500=A27)*'Job Log'!$A$2:$A$500)))
L28: =IF(K28="","",K28-TODAY()) | R28: =IF(A28="","",COUNTIF('Job Log'!$E:$E,A28)) | S28: =IF(A28="","",SUMIFS('Job Log'!$H:$H,'Job Log'!$E:$E,A28)) | T28: =IF(OR(A28="",COUNTIFS('Job Log'!$E:$E,A28,'Job Log'!$I:$I,">0")=0),"",AVERAGEIFS('Job Log'!$I:$I,'Job Log'!$E:$E,A28,'Job Log'!$I:$I,">0")) | U28: =IF(OR(A28="",COUNTIF('Job Log'!$E:$E,A28)=0),"",SUMPRODUCT(MAX(('Job Log'!$E$2:$E$500=A28)*'Job Log'!$A$2:$A$500)))
L29: =IF(K29="","",K29-TODAY()) | R29: =IF(A29="","",COUNTIF('Job Log'!$E:$E,A29)) | S29: =IF(A29="","",SUMIFS('Job Log'!$H:$H,'Job Log'!$E:$E,A29)) | T29: =IF(OR(A29="",COUNTIFS('Job Log'!$E:$E,A29,'Job Log'!$I:$I,">0")=0),"",AVERAGEIFS('Job Log'!$I:$I,'Job Log'!$E:$E,A29,'Job Log'!$I:$I,">0")) | U29: =IF(OR(A29="",COUNTIF('Job Log'!$E:$E,A29)=0),"",SUMPRODUCT(MAX(('Job Log'!$E$2:$E$500=A29)*'Job Log'!$A$2:$A$500)))
L30: =IF(K30="","",K30-TODAY()) | R30: =IF(A30="","",COUNTIF('Job Log'!$E:$E,A30)) | S30: =IF(A30="","",SUMIFS('Job Log'!$H:$H,'Job Log'!$E:$E,A30)) | T30: =IF(OR(A30="",COUNTIFS('Job Log'!$E:$E,A30,'Job Log'!$I:$I,">0")=0),"",AVERAGEIFS('Job Log'!$I:$I,'Job Log'!$E:$E,A30,'Job Log'!$I:$I,">0")) | U30: =IF(OR(A30="",COUNTIF('Job Log'!$E:$E,A30)=0),"",SUMPRODUCT(MAX(('Job Log'!$E$2:$E$500=A30)*'Job Log'!$A$2:$A$500)))
L31: =IF(K31="","",K31-TODAY()) | R31: =IF(A31="","",COUNTIF('Job Log'!$E:$E,A31)) | S31: =IF(A31="","",SUMIFS('Job Log'!$H:$H,'Job Log'!$E:$E,A31)) | T31: =IF(OR(A31="",COUNTIFS('Job Log'!$E:$E,A31,'Job Log'!$I:$I,">0")=0),"",AVERAGEIFS('Job Log'!$I:$I,'Job Log'!$E:$E,A31,'Job Log'!$I:$I,">0")) | U31: =IF(OR(A31="",COUNTIF('Job Log'!$E:$E,A31)=0),"",SUMPRODUCT(MAX(('Job Log'!$E$2:$E$500=A31)*'Job Log'!$A$2:$A$500)))
L32: =IF(K32="","",K32-TODAY()) | R32: =IF(A32="","",COUNTIF('Job Log'!$E:$E,A32)) | S32: =IF(A32="","",SUMIFS('Job Log'!$H:$H,'Job Log'!$E:$E,A32)) | T32: =IF(OR(A32="",COUNTIFS('Job Log'!$E:$E,A32,'Job Log'!$I:$I,">0")=0),"",AVERAGEIFS('Job Log'!$I:$I,'Job Log'!$E:$E,A32,'Job Log'!$I:$I,">0")) | U32: =IF(OR(A32="",COUNTIF('Job Log'!$E:$E,A32)=0),"",SUMPRODUCT(MAX(('Job Log'!$E$2:$E$500=A32)*'Job Log'!$A$2:$A$500)))
L33: =IF(K33="","",K33-TODAY()) | R33: =IF(A33="","",COUNTIF('Job Log'!$E:$E,A33)) | S33: =IF(A33="","",SUMIFS('Job Log'!$H:$H,'Job Log'!$E:$E,A33)) | T33: =IF(OR(A33="",COUNTIFS('Job Log'!$E:$E,A33,'Job Log'!$I:$I,">0")=0),"",AVERAGEIFS('Job Log'!$I:$I,'Job Log'!$E:$E,A33,'Job Log'!$I:$I,">0")) | U33: =IF(OR(A33="",COUNTIF('Job Log'!$E:$E,A33)=0),"",SUMPRODUCT(MAX(('Job Log'!$E$2:$E$500=A33)*'Job Log'!$A$2:$A$500)))
L34: =IF(K34="","",K34-TODAY()) | R34: =IF(A34="","",COUNTIF('Job Log'!$E:$E,A34)) | S34: =IF(A34="","",SUMIFS('Job Log'!$H:$H,'Job Log'!$E:$E,A34)) | T34: =IF(OR(A34="",COUNTIFS('Job Log'!$E:$E,A34,'Job Log'!$I:$I,">0")=0),"",AVERAGEIFS('Job Log'!$I:$I,'Job Log'!$E:$E,A34,'Job Log'!$I:$I,">0")) | U34: =IF(OR(A34="",COUNTIF('Job Log'!$E:$E,A34)=0),"",SUMPRODUCT(MAX(('Job Log'!$E$2:$E$500=A34)*'Job Log'!$A$2:$A$500)))
L35: =IF(K35="","",K35-TODAY()) | R35: =IF(A35="","",COUNTIF('Job Log'!$E:$E,A35)) | S35: =IF(A35="","",SUMIFS('Job Log'!$H:$H,'Job Log'!$E:$E,A35)) | T35: =IF(OR(A35="",COUNTIFS('Job Log'!$E:$E,A35,'Job Log'!$I:$I,">0")=0),"",AVERAGEIFS('Job Log'!$I:$I,'Job Log'!$E:$E,A35,'Job Log'!$I:$I,">0")) | U35: =IF(OR(A35="",COUNTIF('Job Log'!$E:$E,A35)=0),"",SUMPRODUCT(MAX(('Job Log'!$E$2:$E$500=A35)*'Job Log'!$A$2:$A$500)))
L36: =IF(K36="","",K36-TODAY()) | R36: =IF(A36="","",COUNTIF('Job Log'!$E:$E,A36)) | S36: =IF(A36="","",SUMIFS('Job Log'!$H:$H,'Job Log'!$E:$E,A36)) | T36: =IF(OR(A36="",COUNTIFS('Job Log'!$E:$E,A36,'Job Log'!$I:$I,">0")=0),"",AVERAGEIFS('Job Log'!$I:$I,'Job Log'!$E:$E,A36,'Job Log'!$I:$I,">0")) | U36: =IF(OR(A36="",COUNTIF('Job Log'!$E:$E,A36)=0),"",SUMPRODUCT(MAX(('Job Log'!$E$2:$E$500=A36)*'Job Log'!$A$2:$A$500)))
L37: =IF(K37="","",K37-TODAY()) | R37: =IF(A37="","",COUNTIF('Job Log'!$E:$E,A37)) | S37: =IF(A37="","",SUMIFS('Job Log'!$H:$H,'Job Log'!$E:$E,A37)) | T37: =IF(OR(A37="",COUNTIFS('Job Log'!$E:$E,A37,'Job Log'!$I:$I,">0")=0),"",AVERAGEIFS('Job Log'!$I:$I,'Job Log'!$E:$E,A37,'Job Log'!$I:$I,">0")) | U37: =IF(OR(A37="",COUNTIF('Job Log'!$E:$E,A37)=0),"",SUMPRODUCT(MAX(('Job Log'!$E$2:$E$500=A37)*'Job Log'!$A$2:$A$500)))
... L41: =IF(K41="","",K41-TODAY()) | R41: =IF(A41="","",COUNTIF('Job Log'!$E:$E,A41)) | S41: =IF(A41="","",SUMIFS('Job Log'!$H:$H,'Job Log'!$E:$E,A41)) | T41: =IF(OR(A41="",COUNTIFS('Job Log'!$E:$E,A41,'Job Log'!$I:$I,">0")=0),"",AVERAGEIFS('Job Log'!$I:$I,'Job Log'!$E:$E,A41,'Job Log'!$I:$I,">0")) | U41: =IF(OR(A41="",COUNTIF('Job Log'!$E:$E,A41)=0),"",SUMPRODUCT(MAX(('Job Log'!$E$2:$E$500=A41)*'Job Log'!$A$2:$A$500)))

Sheet Job Log
A1: Date | B1: Property | C1: Issue (short) | D1: Trade | E1: Vendor | F1: Urgency | G1: Quote / NTE | H1: Paid | I1: Rating 1-5 | J1: Permit needed? | K1: Tenant caused? | L1: Notes / what was done | N1: Spend summary
A2: 46266 | B2: Example: Seminole Hts | C2: Kitchen faucet dripping | D2: Handyman | E2: Example: Mike R. | F2: Routine | G2: 120 | H2: 110 | I2: 5 | J2: No | K2: No | L2: Replaced cartridge. 45 min. | N2: Total paid, all time | O2: =SUM(H2:H500) -> 110
N3: Total paid, last 90 days | O3: =SUMIFS(H2:H500,A2:A500,">="&(TODAY()-90)) -> 110
N4: Jobs, last 90 days | O4: =COUNTIFS(A2:A500,">="&(TODAY()-90),H2:H500,"<>") -> 1
N5: Avg cost per job, last 90 days | O5: =IF(O4=0,0,O3/O4) -> 110
N6: Emergency jobs, last 90 days | O6: =COUNTIFS(A2:A500,">="&(TODAY()-90),F2:F500,"Emergency") -> 0

Sheet Triage Guide
A1: Issue tenant reports | B1: Send this trade first | C1: FL license legally required? | D1: Urgency | E1: Typical Tampa cost (2026) | F1: Before you dispatch
A2: No water / major leak / burst pipe | B2: Plumber | C2: Yes. Any pipe cutting or drain alteration. | D2: Emergency | E2: $150-400 service + repair | F2: Have tenant shut main valve. Show them where it is on move-in.
A3: Clogged sink / tub drain | B3: Handyman | C3: No, if snaking only. Yes if pipe is opened. | D3: This week | E3: $75-250 | F3: Ask tenant to try a plunger first. Recurring clogs on cast iron = plumber camera.
A4: Running or leaking toilet | B4: Handyman | C4: No. Flapper, fill valve, wax ring are all handyman. | D4: This week | E4: $100-200 | F4: Photo of tank interior. Usually a $15 part.
A5: Dripping faucet / bad cartridge | B5: Handyman | C5: No. Fixture replacement is exempt. | D5: Routine | E5: $90-180 | F5: Confirm brand from photo so he brings the cartridge.
A6: Water heater dead | B6: Plumber | C6: Yes. Permit required for replacement in Tampa. | D6: 24 hr | E6: $1,200-2,200 installed (40 gal) | F6: Check age on the label. Over 12 years, replace, do not repair.
A7: Garbage disposal jammed / dead | B7: Handyman | C7: No. Like-for-like swap is exempt. | D7: Routine | E7: $150-300 installed | F7: Reset button and allen key first, tenant can try.
A8: No power to whole unit | B8: Electrician | C8: Yes. | D8: Emergency | E8: $100-200 diagnostic | F8: Have tenant check main breaker and call TECO first. Half of these are utility side.
A9: One outlet / switch dead, breaker trips | B9: Electrician | C9: Yes. Anything inside the box or panel. | D9: 24 hr | E9: $150-350 | F9: GFCI reset first. Tenant can try every GFCI in kitchen, baths, garage.
A10: Light fixture / ceiling fan swap | B10: Handyman | C10: Grey area. Like-for-like swap is commonly done by handymen. New circuit = electrician. | D10: Routine | E10: $75-150 labor | F10: Only if replacing an existing fixture on existing wiring.
A11: AC not cooling | B11: HVAC | C11: Yes. Refrigerant and electrical work need a license. | D11: Emergency (Jun-Oct) | E11: $100-150 diagnostic, $300-800 common repairs | F11: Tenant: change filter, check thermostat batteries, check breaker, check drain line float switch. Solves 30% of calls.
A12: AC drain line clogged / water at air handler | B12: Handyman | C12: No. Clearing the condensate line is maintenance. | D12: 24 hr | E12: $75-150 | F12: Put a $10 float switch on every unit. Vinegar in drain line quarterly.
... A21: Anything over $1,000 or needing a permit | B21: GC or licensed trade | C21: Yes. FL law, no exceptions. | D21: Varies | E21: Get 3 quotes | F21: Verify license and insurance again even for a bench vendor. Pull permit in owner or contractor name, never tenant.
A23: Sources: Florida Statute 489 ($1,000 handyman threshold; licensed trades for plumbing, electrical, HVAC, roofing, pest). Cost ranges from HomeGuide, Angi, Homeyou 2026 Tampa and national data. Ranges are estimates, replace with your Job Log averages.

Sheet Tampa Sourcing
A1: Rank | B1: Channel | C1: Best for | D1: Cost | E1: Link | F1: How to work it
A2: 1 | B2: Tampa REIA (Tampa Real Estate Investors Alliance) | C2: Every trade. Vendors here already work for landlords, so they know the volume-rate game. | D2: Meetup free, membership ~$100/yr | E2: https://tampareia.com/ | F2: Go to one monthly meeting. Ask three investors with 10+ doors who they use for plumbing, electric, and handyman. Write down every name that comes up twice.
A3: 2 | B3: Tampa Bay REIA (TBREIA) | C3: Same as above, different crowd. Sub-groups across the Bay. | D3: Meetup free | E3: https://www.meetup.com/tampabayreia/ | F3: Post in the group: 'Looking for a licensed plumber who works with investors in [neighborhood].' Investor referrals beat homeowner referrals.
A4: 3 | B4: Other landlords in your ZIP | C4: The cheapest reliable people. Nobody advertises them. | D4: Free | F4: Knock on the door of the other rental on your street, or ask your property's previous owner. One good handyman referral is worth the whole list.
A5: 4 | B5: Facebook groups: search 'Tampa landlord', 'Tampa Bay real estate investors', 'Hillsborough County homeowners' | C5: Handyman, lawn, cleaner, appliance | D5: Free | E5: https://www.facebook.com/groups/search/groups/?q=tampa%20landlord | F5: Search the group history before posting; the same 5 names get recommended every month. Ignore anyone who replies 'DM me' with no company name.
A6: 5 | B6: Nextdoor (set to your rental's neighborhood) | C6: Handyman, lawn, pressure wash, cleaner | D6: Free | E6: https://nextdoor.com/ | F6: Neighbors recommend people who show up. Good for the sub-$1,000 handyman tier only.
A7: 6 | B7: Thumbtack | C7: Handyman, cleaner, appliance, junk removal | D7: Free to browse, pros pay per lead | E7: https://www.thumbtack.com/fl/tampa/ | F7: Fast quotes, good for filling a backup slot. Sort by reviews with 50+, then verify license yourself. Do not rely on Thumbtack's badge.
A8: 7 | B8: Angi / HomeAdvisor | C8: Licensed trades (plumber, electrician, HVAC, roofer) | D8: Free | E8: https://www.angi.com/companylist/tampa/ | F8: Pricier tier. Use it for the licensed backup, not the primary. Angi-listed shops rarely negotiate.
A9: 8 | B9: Home Depot Pro Referral | C9: Licensed trades for permitted work | D9: Free | E9: https://www.homedepot.com/services/ | F9: Pre-screened for license and insurance. Prices are mid-market. Useful when you need a permit pulled fast.
A10: 9 | B10: Google Maps, search '[trade] near [rental ZIP]' and sort by rating | C10: Any | D10: Free | E10: https://www.google.com/maps | F10: Filter for 4.7+ with 100+ reviews AND a real address. Read the 1-star reviews for the pattern (no-shows vs pricing).
A11: 10 | B11: TaskRabbit | C11: Furniture assembly, mounting, moving help, minor handyman | D11: Taskers set hourly rate | E11: https://www.taskrabbit.com/locations/tampa | F11: Fine for turnover odd jobs. Not for plumbing, electric, or anything on a ladder over 6 ft.
A12: 11 | B12: Lula (maintenance coordination, covers Tampa) | C12: The 'always have someone' backstop. They take the tenant call, triage, dispatch a vetted pro, bill you. | D12: Per-job pricing plus service fee; ask for current terms | E12: https://lula.life/services | F12: Best once you are past ~10 doors or living out of state. Set a Not-To-Exceed and they call before exceeding it. Also available through TurboTenant as Maintenance Plus.
A13: 12 | B13: Latchel | C13: Same idea as Lula: 24/7 tenant maintenance line and dispatch | D13: Monthly per unit, ask for a quote | E13: https://latchel.com/ | F13: Compare against Lula. Ask both which Tampa vendors they actually dispatch and whether you can add your own bench.
A14: 13 | B14: Hillsborough County licensed contractor list | C14: Confirms a name is legit, also a way to find licensed locals | D14: Free | E14: https://hcfl.gov/businesses/hillsgovhub/contractor-licensing | F14: Search by trade to find registered locals in your area. Cross-check with reviews.

Sheet Vetting Checklist
A1: Step | B1: Check | C1: Where (free lookup) | D1: Link | E1: Pass / fail rule
A2: 1 | B2: State license active (plumber, electrician, HVAC, roofer, GC, pest) | C2: Florida DBPR license search. Search by name or license number. | D2: https://www.myfloridalicense.com/wl11.asp | E2: Status must read Current, Active. Note the expiry date and any discipline. Null and Void or Inactive = fail.
A3: 2 | B3: County registration (for county-registered, not state-certified, contractors) | C3: HillsGovHub record search, Contractor Licensing. | D3: https://hcfl.gov/businesses/hillsgovhub/contractor-licensing | E3: If they hold a Hillsborough registration rather than a state certification, it must be active here. Registered contractors can only work inside the county.
A4: 3 | B4: General liability insurance | C4: Ask for a Certificate of Insurance (COI) with you named as certificate holder. | E4: Minimum $300k GL for handyman, $1M for licensed trades. Enter the expiry on the Bench so the cell turns red 30 days out.
A5: 4 | B5: Workers comp coverage or exemption | C5: Florida DWC Proof of Coverage database. Search by business name. | D5: https://dwcdataportal.fldfs.com/ProofOfCoverage.aspx | E5: Either an active policy or a current exemption on file. A solo handyman with an exemption is fine. A crew with no policy is your liability if someone gets hurt.
A6: 5 | B6: Business is real | C6: Sunbiz (Florida Division of Corporations). | D6: https://search.sunbiz.org/Inquiry/CorporationSearch/ByName | E6: Active LLC or Inc matching the name on the COI. Not required for a solo handyman, but a plus.
A7: 6 | B7: Reputation | C7: Google reviews, BBB, and the REIA group history. | D7: https://www.bbb.org/local-bbb/bbb-of-west-florida | E7: Read the 1-star reviews. No-shows and surprise charges are the deal-breakers. Bad grammar in a reply is not.
A8: 7 | B8: Trial job | C8: Give them one small, non-urgent job at one property. | E8: Judge on: showed up when they said, sent a photo when done, invoice matched quote. Pass all three = Primary or Backup. Fail any = Retired.
A9: 8 | B9: Rate agreement | C9: Text or email, kept in the Notes column. | E9: Agree hourly or flat rate, trip charge, and that you are called before any job exceeds the NTE. Ask for a volume rate: 'I have X doors, what is your rate for a landlord who sends you everything?'
A11: Tampa-specific notes
A12: City of Tampa proper permits through the City of Tampa Accela portal, not HillsGovHub. Unincorporated Hillsborough (Brandon, Riverview, Town 'n' Country, Carrollwood) uses HillsGovHub. Check which one your address falls under before a permitted job.
A13: Hurricane season is June 1 to Nov 30. Roofers, fence crews and tree services book out weeks after any named storm. Get roof and tree work done in March-May.
A14: AC failures spike June-September. A backup HVAC vendor is not optional in Tampa. Float switches on every air handler prevent the most common ceiling-water call.
A15: Older Tampa housing (Seminole Heights, Ybor, South Tampa bungalows) has cast-iron drain lines and sometimes knob-and-tube or aluminum wiring. Ask the vendor if they have worked on it before you send them.
A16: Florida has no handyman license. The $1,000 total-job threshold and the trade rules are state law (Ch. 489). An unlicensed person doing licensed work voids your ability to enforce the contract and can affect insurance claims.
